{
  "project_info": {
    "project_number": "809795775142",
    "project_id": "servare-bb792",
    "storage_bucket": "servare-bb792.firebasestorage.app"
  },
  "client": [
    {
      "client_info": {
        "mobilesdk_app_id": "1:809795775142:android:20c5a1d8c77f6867c86267",
        "android_client_info": {
          "package_name": "com.servare.ServareApp"
        }
      },
      "oauth_client": [],
      "api_key": [
        {
          "current_key": "AIzaSyAOvZ33YmgXT5tKmbbs2xDL7JQ88AiFAGM"
        }
      ],
      "services": {
        "appinvite_service": {
          "other_platform_oauth_client": []
        }
      }
    }
  ],
  "configuration_version": "1"
}